crypto_bot/__init__.py
crypto_bot/_version.py
crypto_bot/api.py
crypto_bot/app.py
crypto_bot/bots.py
crypto_bot/config.py
crypto_bot/connector.py
crypto_bot/countdown.py
crypto_bot/error.py
crypto_bot/exchanges.py
crypto_bot/price_indexer.py
crypto_bot/twitter_collector.py
crypto_bot/bots/__init__.py
crypto_bot/bots/base_bot.py
crypto_bot/bots/bot_globals.py
crypto_bot/bots/countdown.py
crypto_bot/bots/info_bot.py
crypto_bot/bots/message_bot.py
crypto_bot/bots/price_bot.py
crypto_bot/resources/__init__.py
crypto_bot/resources/config_defaults.yaml
crypto_bot/resources/logger_config.yaml
crypto_bot/resources/rules.py
crypto_bot/resources/rules.yaml
crypto_bot/resources/__pycache__/__init__.cpython-36.pyc
crypto_bot/resources/__pycache__/rules.cpython-36.pyc
crypto_bot/resources/static/css/main.css
crypto_bot/resources/static/image/favicon.ico
crypto_bot/resources/static/js/main.js
crypto_bot/resources/templates/index.html
crypto_bot-3.5.4.dist-info/METADATA
crypto_bot-3.5.4.dist-info/WHEEL
crypto_bot-3.5.4.dist-info/top_level.txt
crypto_bot-3.5.4.dist-info/RECORD
