Metadata-Version: 2.1
Name: crypto-bot
Version: 3.5.4
Summary: Crypto Info Bot
Home-page: https://github.com/vossenv/crypto-bot
Maintainer: Danimae Vossen
Maintainer-email: vossen.dm@gmail.com
License: MIT
Platform: UNKNOWN
Requires-Dist: discord
Requires-Dist: pyyaml
Requires-Dist: schema
Requires-Dist: Flask
Requires-Dist: Werkzeug
Requires-Dist: requests
Requires-Dist: ruamel.yaml
Requires-Dist: python-dateutil
Requires-Dist: pytz
Requires-Dist: python-twitter
Requires-Dist: emoji
Provides-Extra: setup
Requires-Dist: wheel ; extra == 'setup'
Requires-Dist: twine ; extra == 'setup'
